Metadata-Version: 1.0
Name: packaging-example
Version: 0.1.1
Summary: Example on packaging in Python3
Home-page: https://github.com/geowatson/packaging-example
Author: George Poputnikov
Author-email: g.poputnikov@innopolis.ru
License: MIT
Platform: UNKNOWN
